[{"frame":4,"entryIdx":0},{"frame":5,"entryIdx":973},{"frame":6,"entryIdx":974},{"frame":7,"entryIdx":975},{"frame":8,"entryIdx":976},{"frame":9,"entryIdx":977},{"frame":10,"entryIdx":978},{"frame":11,"entryIdx":979},{"frame":18,"entryIdx":1076},{"frame":19,"entryIdx":1077},{"frame":20,"entryIdx":1078},{"frame":21,"entryIdx":1079},{"frame":22,"entryIdx":1080},{"frame":23,"entryIdx":1081},{"frame":24,"entryIdx":1082},{"frame":25,"entryIdx":1083},{"frame":26,"entryIdx":1084},{"frame":27,"entryIdx":1085},{"frame":28,"entryIdx":1086},{"frame":29,"entryIdx":1087},{"frame":30,"entryIdx":1088},{"frame":31,"entryIdx":1089},{"frame":32,"entryIdx":1090},{"frame":33,"entryIdx":1091},{"frame":34,"entryIdx":1092},{"frame":35,"entryIdx":1093},{"frame":36,"entryIdx":1094},{"frame":37,"entryIdx":1095},{"frame":38,"entryIdx":1096},{"frame":39,"entryIdx":1097},{"frame":40,"entryIdx":1098},{"frame":41,"entryIdx":1099},{"frame":42,"entryIdx":1100},{"frame":43,"entryIdx":1101},{"frame":44,"entryIdx":1102},{"frame":45,"entryIdx":1103},{"frame":46,"entryIdx":1104},{"frame":47,"entryIdx":1105},{"frame":48,"entryIdx":1106},{"frame":49,"entryIdx":1107},{"frame":50,"entryIdx":1108},{"frame":51,"entryIdx":1109},{"frame":52,"entryIdx":1110},{"frame":53,"entryIdx":1111},{"frame":54,"entryIdx":1112},{"frame":55,"entryIdx":1113},{"frame":56,"entryIdx":1114},{"frame":57,"entryIdx":1115},{"frame":58,"entryIdx":1116},{"frame":59,"entryIdx":1117},{"frame":60,"entryIdx":1118},{"frame":61,"entryIdx":1119},{"frame":62,"entryIdx":1120},{"frame":63,"entryIdx":1121},{"frame":64,"entryIdx":1122},{"frame":65,"entryIdx":1123},{"frame":66,"entryIdx":1124},{"frame":67,"entryIdx":1125},{"frame":68,"entryIdx":1126},{"frame":69,"entryIdx":1127},{"frame":70,"entryIdx":1128},{"frame":71,"entryIdx":1129},{"frame":72,"entryIdx":1130},{"frame":73,"entryIdx":1131},{"frame":74,"entryIdx":1132},{"frame":75,"entryIdx":1133},{"frame":76,"entryIdx":1134},{"frame":77,"entryIdx":1135},{"frame":78,"entryIdx":1136},{"frame":79,"entryIdx":1137},{"frame":80,"entryIdx":1138},{"frame":81,"entryIdx":1139},{"frame":82,"entryIdx":1140},{"frame":83,"entryIdx":1141},{"frame":84,"entryIdx":1142},{"frame":85,"entryIdx":1143},{"frame":86,"entryIdx":1144},{"frame":87,"entryIdx":1145},{"frame":88,"entryIdx":1146},{"frame":89,"entryIdx":1147},{"frame":90,"entryIdx":1148},{"frame":91,"entryIdx":1149},{"frame":92,"entryIdx":1150},{"frame":93,"entryIdx":1151},{"frame":94,"entryIdx":1152},{"frame":95,"entryIdx":1153},{"frame":96,"entryIdx":1154},{"frame":97,"entryIdx":1155},{"frame":98,"entryIdx":1156},{"frame":99,"entryIdx":1157},{"frame":100,"entryIdx":1158},{"frame":101,"entryIdx":1159},{"frame":102,"entryIdx":1160},{"frame":103,"entryIdx":1161},{"frame":104,"entryIdx":1162},{"frame":105,"entryIdx":1163},{"frame":106,"entryIdx":1164},{"frame":107,"entryIdx":1165},{"frame":108,"entryIdx":1166},{"frame":109,"entryIdx":1167},{"frame":110,"entryIdx":1168},{"frame":111,"entryIdx":1169},{"frame":112,"entryIdx":1170},{"frame":113,"entryIdx":1171},{"frame":114,"entryIdx":1172},{"frame":115,"entryIdx":1173},{"frame":116,"entryIdx":1174},{"frame":117,"entryIdx":1175},{"frame":118,"entryIdx":1176},{"frame":119,"entryIdx":1177},{"frame":120,"entryIdx":1178},{"frame":121,"entryIdx":1179},{"frame":122,"entryIdx":1180},{"frame":123,"entryIdx":1181},{"frame":124,"entryIdx":1182},{"frame":125,"entryIdx":1183},{"frame":126,"entryIdx":1184},{"frame":127,"entryIdx":1185},{"frame":128,"entryIdx":1186},{"frame":129,"entryIdx":1187},{"frame":130,"entryIdx":1188},{"frame":131,"entryIdx":1189},{"frame":132,"entryIdx":1190},{"frame":133,"entryIdx":1191},{"frame":134,"entryIdx":1192},{"frame":135,"entryIdx":1193},{"frame":136,"entryIdx":1194},{"frame":137,"entryIdx":1195},{"frame":138,"entryIdx":1196},{"frame":139,"entryIdx":1197},{"frame":140,"entryIdx":1198},{"frame":141,"entryIdx":1292},{"frame":142,"entryIdx":1293},{"frame":143,"entryIdx":1294},{"frame":144,"entryIdx":1295},{"frame":145,"entryIdx":1296},{"frame":146,"entryIdx":1297},{"frame":147,"entryIdx":1298},{"frame":148,"entryIdx":1299},{"frame":149,"entryIdx":1300},{"frame":150,"entryIdx":1301},{"frame":151,"entryIdx":1302},{"frame":152,"entryIdx":1303},{"frame":153,"entryIdx":1304},{"frame":154,"entryIdx":1305},{"frame":155,"entryIdx":1306},{"frame":156,"entryIdx":1307},{"frame":157,"entryIdx":1308},{"frame":158,"entryIdx":1309},{"frame":159,"entryIdx":1310},{"frame":160,"entryIdx":1311},{"frame":161,"entryIdx":1312},{"frame":162,"entryIdx":1313},{"frame":163,"entryIdx":1314},{"frame":164,"entryIdx":1315},{"frame":165,"entryIdx":1316},{"frame":166,"entryIdx":1317},{"frame":167,"entryIdx":1318},{"frame":168,"entryIdx":1319},{"frame":169,"entryIdx":1320},{"frame":170,"entryIdx":1321},{"frame":171,"entryIdx":1322},{"frame":172,"entryIdx":1323},{"frame":173,"entryIdx":1324},{"frame":174,"entryIdx":1325},{"frame":175,"entryIdx":1326},{"frame":176,"entryIdx":1327},{"frame":177,"entryIdx":1328},{"frame":178,"entryIdx":1329},{"frame":179,"entryIdx":1330},{"frame":180,"entryIdx":1331},{"frame":181,"entryIdx":1332},{"frame":182,"entryIdx":1333},{"frame":183,"entryIdx":1334},{"frame":184,"entryIdx":1335},{"frame":185,"entryIdx":1336},{"frame":186,"entryIdx":1337},{"frame":187,"entryIdx":1338},{"frame":188,"entryIdx":1339},{"frame":189,"entryIdx":1340},{"frame":190,"entryIdx":1483},{"frame":191,"entryIdx":1484},{"frame":192,"entryIdx":1485},{"frame":193,"entryIdx":1486},{"frame":194,"entryIdx":1487},{"frame":195,"entryIdx":1488},{"frame":196,"entryIdx":1489},{"frame":197,"entryIdx":1490},{"frame":198,"entryIdx":1491},{"frame":199,"entryIdx":1492},{"frame":200,"entryIdx":1493},{"frame":201,"entryIdx":1494},{"frame":202,"entryIdx":1495},{"frame":203,"entryIdx":1496},{"frame":204,"entryIdx":1497},{"frame":205,"entryIdx":1498},{"frame":206,"entryIdx":1499},{"frame":207,"entryIdx":1500},{"frame":208,"entryIdx":1501},{"frame":209,"entryIdx":1502},{"frame":210,"entryIdx":1503},{"frame":211,"entryIdx":1504},{"frame":212,"entryIdx":1505},{"frame":213,"entryIdx":1506},{"frame":214,"entryIdx":1507},{"frame":215,"entryIdx":1508},{"frame":216,"entryIdx":1509},{"frame":217,"entryIdx":1510},{"frame":218,"entryIdx":1511},{"frame":219,"entryIdx":1512},{"frame":220,"entryIdx":1513},{"frame":221,"entryIdx":1514},{"frame":222,"entryIdx":1515},{"frame":223,"entryIdx":1516},{"frame":224,"entryIdx":1517},{"frame":225,"entryIdx":1518},{"frame":226,"entryIdx":1519},{"frame":227,"entryIdx":1520},{"frame":228,"entryIdx":1521},{"frame":229,"entryIdx":1522},{"frame":230,"entryIdx":1523},{"frame":231,"entryIdx":1524},{"frame":232,"entryIdx":1525},{"frame":233,"entryIdx":1526},{"frame":234,"entryIdx":1527},{"frame":235,"entryIdx":1528},{"frame":236,"entryIdx":1529},{"frame":237,"entryIdx":1530},{"frame":238,"entryIdx":1531},{"frame":239,"entryIdx":1532},{"frame":240,"entryIdx":1533},{"frame":241,"entryIdx":1534},{"frame":242,"entryIdx":1535},{"frame":243,"entryIdx":1536},{"frame":244,"entryIdx":1537},{"frame":245,"entryIdx":1538},{"frame":246,"entryIdx":1539},{"frame":247,"entryIdx":1540},{"frame":248,"entryIdx":1541},{"frame":249,"entryIdx":1542},{"frame":250,"entryIdx":1543},{"frame":251,"entryIdx":1544},{"frame":252,"entryIdx":1545},{"frame":253,"entryIdx":1546},{"frame":254,"entryIdx":1547},{"frame":255,"entryIdx":1548},{"frame":256,"entryIdx":1549},{"frame":257,"entryIdx":1550},{"frame":258,"entryIdx":1551},{"frame":259,"entryIdx":1552},{"frame":260,"entryIdx":1553},{"frame":261,"entryIdx":1554},{"frame":262,"entryIdx":1555},{"frame":263,"entryIdx":1556},{"frame":264,"entryIdx":1557},{"frame":265,"entryIdx":1558},{"frame":266,"entryIdx":1559},{"frame":267,"entryIdx":1560},{"frame":268,"entryIdx":1561},{"frame":269,"entryIdx":1562},{"frame":270,"entryIdx":1563},{"frame":271,"entryIdx":1564},{"frame":272,"entryIdx":1565},{"frame":273,"entryIdx":1566},{"frame":274,"entryIdx":1567},{"frame":275,"entryIdx":1568},{"frame":276,"entryIdx":1569},{"frame":277,"entryIdx":1570},{"frame":278,"entryIdx":1571},{"frame":279,"entryIdx":1572},{"frame":280,"entryIdx":1573},{"frame":281,"entryIdx":1574},{"frame":282,"entryIdx":1575},{"frame":283,"entryIdx":1576},{"frame":284,"entryIdx":1577},{"frame":285,"entryIdx":1578},{"frame":286,"entryIdx":1579},{"frame":287,"entryIdx":1580},{"frame":288,"entryIdx":1581},{"frame":289,"entryIdx":1582},{"frame":290,"entryIdx":1583},{"frame":291,"entryIdx":1584},{"frame":292,"entryIdx":1585},{"frame":293,"entryIdx":1586},{"frame":294,"entryIdx":1587},{"frame":295,"entryIdx":1588},{"frame":296,"entryIdx":1589},{"frame":297,"entryIdx":1590},{"frame":298,"entryIdx":1591},{"frame":299,"entryIdx":1592},{"frame":300,"entryIdx":1593},{"frame":301,"entryIdx":1874},{"frame":302,"entryIdx":1875},{"frame":303,"entryIdx":1876},{"frame":304,"entryIdx":1877},{"frame":305,"entryIdx":1878},{"frame":306,"entryIdx":1879},{"frame":307,"entryIdx":1880},{"frame":308,"entryIdx":1881},{"frame":309,"entryIdx":1882},{"frame":310,"entryIdx":1883},{"frame":311,"entryIdx":1884},{"frame":312,"entryIdx":1885},{"frame":313,"entryIdx":1886},{"frame":314,"entryIdx":1887},{"frame":315,"entryIdx":1888},{"frame":316,"entryIdx":1889},{"frame":317,"entryIdx":1890},{"frame":318,"entryIdx":1891},{"frame":319,"entryIdx":1892},{"frame":320,"entryIdx":1893},{"frame":321,"entryIdx":1894},{"frame":322,"entryIdx":1895},{"frame":323,"entryIdx":1896},{"frame":324,"entryIdx":1897},{"frame":325,"entryIdx":1898},{"frame":326,"entryIdx":1899},{"frame":327,"entryIdx":1900},{"frame":328,"entryIdx":1901},{"frame":329,"entryIdx":1902},{"frame":330,"entryIdx":1903},{"frame":331,"entryIdx":1904},{"frame":332,"entryIdx":1905},{"frame":333,"entryIdx":1906},{"frame":334,"entryIdx":1907},{"frame":335,"entryIdx":1908},{"frame":336,"entryIdx":1909},{"frame":337,"entryIdx":2188},{"frame":338,"entryIdx":2189},{"frame":339,"entryIdx":2190},{"frame":340,"entryIdx":2191},{"frame":341,"entryIdx":2192},{"frame":342,"entryIdx":2193},{"frame":343,"entryIdx":2194},{"frame":344,"entryIdx":2195},{"frame":345,"entryIdx":2196},{"frame":346,"entryIdx":2197},{"frame":347,"entryIdx":2198},{"frame":348,"entryIdx":2199},{"frame":349,"entryIdx":2200},{"frame":350,"entryIdx":2201},{"frame":351,"entryIdx":2202},{"frame":352,"entryIdx":2203},{"frame":353,"entryIdx":2204},{"frame":354,"entryIdx":2205},{"frame":355,"entryIdx":2206},{"frame":356,"entryIdx":2207},{"frame":357,"entryIdx":2208},{"frame":358,"entryIdx":2209},{"frame":359,"entryIdx":2210},{"frame":360,"entryIdx":2211},{"frame":361,"entryIdx":2212},{"frame":362,"entryIdx":2213},{"frame":363,"entryIdx":2214},{"frame":364,"entryIdx":2215},{"frame":365,"entryIdx":2216},{"frame":366,"entryIdx":2217},{"frame":367,"entryIdx":2218},{"frame":368,"entryIdx":2219},{"frame":369,"entryIdx":2220},{"frame":370,"entryIdx":2221},{"frame":371,"entryIdx":2222},{"frame":372,"entryIdx":2223},{"frame":373,"entryIdx":2224},{"frame":374,"entryIdx":2464},{"frame":375,"entryIdx":2465},{"frame":376,"entryIdx":2466},{"frame":377,"entryIdx":2467},{"frame":378,"entryIdx":2468},{"frame":379,"entryIdx":2469},{"frame":380,"entryIdx":2470},{"frame":381,"entryIdx":2471},{"frame":382,"entryIdx":2472},{"frame":383,"entryIdx":2473},{"frame":384,"entryIdx":2474},{"frame":385,"entryIdx":2475},{"frame":386,"entryIdx":2476},{"frame":387,"entryIdx":2477},{"frame":388,"entryIdx":2478},{"frame":389,"entryIdx":2479},{"frame":390,"entryIdx":2480},{"frame":391,"entryIdx":2481},{"frame":392,"entryIdx":2482},{"frame":393,"entryIdx":2483},{"frame":394,"entryIdx":2484},{"frame":395,"entryIdx":2485},{"frame":396,"entryIdx":2486},{"frame":397,"entryIdx":2487},{"frame":398,"entryIdx":2488},{"frame":399,"entryIdx":2489},{"frame":400,"entryIdx":2490},{"frame":401,"entryIdx":2491},{"frame":402,"entryIdx":2492},{"frame":403,"entryIdx":2493},{"frame":404,"entryIdx":2494},{"frame":405,"entryIdx":2495},{"frame":406,"entryIdx":2496},{"frame":407,"entryIdx":2497},{"frame":408,"entryIdx":2498},{"frame":409,"entryIdx":2499},{"frame":410,"entryIdx":2500},{"frame":411,"entryIdx":2501},{"frame":412,"entryIdx":2502},{"frame":413,"entryIdx":2503},{"frame":414,"entryIdx":2504},{"frame":415,"entryIdx":2532},{"frame":416,"entryIdx":2533},{"frame":417,"entryIdx":2534},{"frame":418,"entryIdx":2535},{"frame":419,"entryIdx":2536},{"frame":420,"entryIdx":2537},{"frame":421,"entryIdx":2538},{"frame":422,"entryIdx":2539},{"frame":423,"entryIdx":2540},{"frame":424,"entryIdx":2541},{"frame":425,"entryIdx":2542},{"frame":426,"entryIdx":2543},{"frame":427,"entryIdx":2544},{"frame":428,"entryIdx":2545},{"frame":429,"entryIdx":2546},{"frame":430,"entryIdx":2547},{"frame":431,"entryIdx":2548},{"frame":432,"entryIdx":2549},{"frame":433,"entryIdx":2550},{"frame":434,"entryIdx":2551},{"frame":435,"entryIdx":2552},{"frame":436,"entryIdx":2553},{"frame":437,"entryIdx":2554},{"frame":438,"entryIdx":2555},{"frame":439,"entryIdx":2556},{"frame":440,"entryIdx":2557},{"frame":441,"entryIdx":2558},{"frame":442,"entryIdx":2559},{"frame":443,"entryIdx":2560},{"frame":444,"entryIdx":2561},{"frame":445,"entryIdx":2562},{"frame":446,"entryIdx":2563},{"frame":447,"entryIdx":2564},{"frame":448,"entryIdx":2565},{"frame":449,"entryIdx":2566},{"frame":450,"entryIdx":2567},{"frame":451,"entryIdx":2568},{"frame":452,"entryIdx":2569},{"frame":453,"entryIdx":2570},{"frame":454,"entryIdx":2571},{"frame":455,"entryIdx":2572},{"frame":456,"entryIdx":2573},{"frame":457,"entryIdx":2574},{"frame":458,"entryIdx":2575},{"frame":459,"entryIdx":2576},{"frame":460,"entryIdx":2577},{"frame":461,"entryIdx":2578},{"frame":462,"entryIdx":2579},{"frame":463,"entryIdx":2580},{"frame":464,"entryIdx":2581},{"frame":465,"entryIdx":2582},{"frame":466,"entryIdx":2583},{"frame":467,"entryIdx":2584},{"frame":468,"entryIdx":2585},{"frame":469,"entryIdx":2586},{"frame":470,"entryIdx":2587},{"frame":471,"entryIdx":2588},{"frame":472,"entryIdx":2589},{"frame":473,"entryIdx":2590},{"frame":474,"entryIdx":2591},{"frame":475,"entryIdx":2592},{"frame":476,"entryIdx":2593},{"frame":477,"entryIdx":2594},{"frame":478,"entryIdx":2595},{"frame":479,"entryIdx":2596},{"frame":480,"entryIdx":2597},{"frame":481,"entryIdx":2598},{"frame":482,"entryIdx":2599},{"frame":483,"entryIdx":2600},{"frame":484,"entryIdx":2601},{"frame":485,"entryIdx":2602},{"frame":486,"entryIdx":2603},{"frame":487,"entryIdx":2604},{"frame":488,"entryIdx":2605},{"frame":489,"entryIdx":2606},{"frame":490,"entryIdx":2607},{"frame":491,"entryIdx":2608},{"frame":492,"entryIdx":2609},{"frame":493,"entryIdx":2610},{"frame":494,"entryIdx":2611},{"frame":495,"entryIdx":2612},{"frame":496,"entryIdx":2613},{"frame":497,"entryIdx":2614},{"frame":498,"entryIdx":2615},{"frame":499,"entryIdx":2616},{"frame":500,"entryIdx":2617},{"frame":501,"entryIdx":2618},{"frame":502,"entryIdx":2619},{"frame":503,"entryIdx":2620},{"frame":504,"entryIdx":2621},{"frame":505,"entryIdx":2622},{"frame":506,"entryIdx":2623},{"frame":507,"entryIdx":2624},{"frame":508,"entryIdx":2625},{"frame":509,"entryIdx":2626},{"frame":510,"entryIdx":2627},{"frame":511,"entryIdx":2628},{"frame":512,"entryIdx":2629},{"frame":513,"entryIdx":2630},{"frame":514,"entryIdx":2631},{"frame":515,"entryIdx":2632},{"frame":516,"entryIdx":2633},{"frame":517,"entryIdx":2634},{"frame":518,"entryIdx":2635},{"frame":519,"entryIdx":2636},{"frame":520,"entryIdx":2637},{"frame":521,"entryIdx":2638},{"frame":522,"entryIdx":2639},{"frame":523,"entryIdx":2640},{"frame":524,"entryIdx":2641},{"frame":525,"entryIdx":2642},{"frame":526,"entryIdx":2643},{"frame":527,"entryIdx":2644},{"frame":528,"entryIdx":2645},{"frame":529,"entryIdx":2646},{"frame":530,"entryIdx":2647},{"frame":531,"entryIdx":2648},{"frame":532,"entryIdx":2649},{"frame":533,"entryIdx":2650},{"frame":534,"entryIdx":3011},{"frame":535,"entryIdx":3012},{"frame":536,"entryIdx":3013},{"frame":537,"entryIdx":3014},{"frame":538,"entryIdx":3015},{"frame":539,"entryIdx":3016},{"frame":540,"entryIdx":3017},{"frame":541,"entryIdx":3018},{"frame":542,"entryIdx":3019},{"frame":543,"entryIdx":3020},{"frame":544,"entryIdx":3021},{"frame":545,"entryIdx":3022},{"frame":546,"entryIdx":3023},{"frame":547,"entryIdx":3024},{"frame":548,"entryIdx":3025},{"frame":549,"entryIdx":3026},{"frame":550,"entryIdx":3027},{"frame":551,"entryIdx":3028},{"frame":552,"entryIdx":3029},{"frame":553,"entryIdx":3030},{"frame":554,"entryIdx":3031},{"frame":555,"entryIdx":3032},{"frame":556,"entryIdx":3033},{"frame":557,"entryIdx":3034},{"frame":558,"entryIdx":3035},{"frame":559,"entryIdx":3036},{"frame":560,"entryIdx":3037},{"frame":561,"entryIdx":3038},{"frame":562,"entryIdx":3039},{"frame":563,"entryIdx":3040},{"frame":564,"entryIdx":3041},{"frame":565,"entryIdx":3042},{"frame":566,"entryIdx":3043},{"frame":567,"entryIdx":3044},{"frame":568,"entryIdx":3045},{"frame":569,"entryIdx":3248},{"frame":570,"entryIdx":3249},{"frame":571,"entryIdx":3250},{"frame":572,"entryIdx":3251},{"frame":573,"entryIdx":3252},{"frame":574,"entryIdx":3253},{"frame":575,"entryIdx":3254},{"frame":576,"entryIdx":3255},{"frame":577,"entryIdx":3256},{"frame":578,"entryIdx":3257},{"frame":579,"entryIdx":3258},{"frame":580,"entryIdx":3259},{"frame":581,"entryIdx":3260},{"frame":582,"entryIdx":3261},{"frame":583,"entryIdx":3262},{"frame":584,"entryIdx":3263},{"frame":585,"entryIdx":3264},{"frame":586,"entryIdx":3265},{"frame":587,"entryIdx":3266},{"frame":588,"entryIdx":3267},{"frame":589,"entryIdx":3268},{"frame":590,"entryIdx":3269},{"frame":591,"entryIdx":3270},{"frame":592,"entryIdx":3271},{"frame":593,"entryIdx":3272},{"frame":594,"entryIdx":3273},{"frame":595,"entryIdx":3274},{"frame":596,"entryIdx":3275},{"frame":597,"entryIdx":3276},{"frame":598,"entryIdx":3277},{"frame":599,"entryIdx":3278},{"frame":600,"entryIdx":3279},{"frame":601,"entryIdx":3280},{"frame":602,"entryIdx":3281},{"frame":603,"entryIdx":3282},{"frame":604,"entryIdx":3283},{"frame":605,"entryIdx":3284},{"frame":606,"entryIdx":3285},{"frame":607,"entryIdx":3286},{"frame":608,"entryIdx":3287},{"frame":609,"entryIdx":3288},{"frame":610,"entryIdx":3289},{"frame":611,"entryIdx":3290},{"frame":612,"entryIdx":3291},{"frame":613,"entryIdx":3292},{"frame":614,"entryIdx":3293},{"frame":615,"entryIdx":3294},{"frame":616,"entryIdx":3295},{"frame":617,"entryIdx":3296},{"frame":618,"entryIdx":3297},{"frame":619,"entryIdx":3298},{"frame":620,"entryIdx":3299},{"frame":621,"entryIdx":3416},{"frame":622,"entryIdx":3417},{"frame":623,"entryIdx":3418},{"frame":624,"entryIdx":3419},{"frame":625,"entryIdx":3420},{"frame":626,"entryIdx":3421},{"frame":627,"entryIdx":3422},{"frame":628,"entryIdx":3423},{"frame":629,"entryIdx":3424},{"frame":630,"entryIdx":3425},{"frame":631,"entryIdx":3426},{"frame":632,"entryIdx":3427},{"frame":633,"entryIdx":3428},{"frame":634,"entryIdx":3429},{"frame":635,"entryIdx":3430},{"frame":636,"entryIdx":3431},{"frame":637,"entryIdx":3432},{"frame":638,"entryIdx":3433},{"frame":639,"entryIdx":3434},{"frame":640,"entryIdx":3435},{"frame":641,"entryIdx":3436},{"frame":642,"entryIdx":3437},{"frame":643,"entryIdx":3438},{"frame":644,"entryIdx":3439},{"frame":645,"entryIdx":3440},{"frame":646,"entryIdx":3441},{"frame":647,"entryIdx":3442},{"frame":648,"entryIdx":3443},{"frame":649,"entryIdx":3444},{"frame":650,"entryIdx":3445},{"frame":651,"entryIdx":3446},{"frame":652,"entryIdx":3447},{"frame":653,"entryIdx":3448},{"frame":654,"entryIdx":3449},{"frame":655,"entryIdx":3450},{"frame":656,"entryIdx":3451},{"frame":657,"entryIdx":3452},{"frame":658,"entryIdx":3453},{"frame":659,"entryIdx":3454},{"frame":660,"entryIdx":3455},{"frame":661,"entryIdx":3456},{"frame":662,"entryIdx":3457},{"frame":663,"entryIdx":3458},{"frame":664,"entryIdx":3459},{"frame":665,"entryIdx":3460},{"frame":666,"entryIdx":3461},{"frame":667,"entryIdx":3462},{"frame":668,"entryIdx":3463},{"frame":669,"entryIdx":3464},{"frame":670,"entryIdx":3465},{"frame":671,"entryIdx":3466},{"frame":672,"entryIdx":3467},{"frame":673,"entryIdx":3468},{"frame":674,"entryIdx":3469},{"frame":675,"entryIdx":3470},{"frame":676,"entryIdx":3471},{"frame":677,"entryIdx":3472},{"frame":678,"entryIdx":3473},{"frame":679,"entryIdx":3474},{"frame":680,"entryIdx":3475},{"frame":681,"entryIdx":3476},{"frame":682,"entryIdx":3477},{"frame":683,"entryIdx":3478},{"frame":684,"entryIdx":3479},{"frame":685,"entryIdx":3480},{"frame":686,"entryIdx":3481},{"frame":687,"entryIdx":3482},{"frame":688,"entryIdx":3483},{"frame":689,"entryIdx":3484},{"frame":690,"entryIdx":3485},{"frame":691,"entryIdx":3486},{"frame":692,"entryIdx":3487},{"frame":693,"entryIdx":3488},{"frame":694,"entryIdx":3489},{"frame":695,"entryIdx":3490},{"frame":696,"entryIdx":3491},{"frame":697,"entryIdx":3492},{"frame":698,"entryIdx":3493},{"frame":699,"entryIdx":3494},{"frame":700,"entryIdx":3495},{"frame":701,"entryIdx":3496},{"frame":702,"entryIdx":3497},{"frame":703,"entryIdx":3498},{"frame":704,"entryIdx":3499},{"frame":705,"entryIdx":3500},{"frame":706,"entryIdx":3501},{"frame":707,"entryIdx":3502},{"frame":708,"entryIdx":3503},{"frame":709,"entryIdx":3504},{"frame":710,"entryIdx":3505},{"frame":711,"entryIdx":3506},{"frame":712,"entryIdx":3507},{"frame":713,"entryIdx":3508},{"frame":714,"entryIdx":3509},{"frame":715,"entryIdx":3510},{"frame":716,"entryIdx":3511},{"frame":717,"entryIdx":3512},{"frame":718,"entryIdx":3513},{"frame":719,"entryIdx":3514},{"frame":720,"entryIdx":3515},{"frame":721,"entryIdx":3516},{"frame":722,"entryIdx":3517},{"frame":723,"entryIdx":3518},{"frame":724,"entryIdx":3519},{"frame":725,"entryIdx":3520},{"frame":726,"entryIdx":3521},{"frame":727,"entryIdx":3522},{"frame":728,"entryIdx":3523},{"frame":729,"entryIdx":3524},{"frame":730,"entryIdx":3525},{"frame":731,"entryIdx":3526},{"frame":732,"entryIdx":3527},{"frame":733,"entryIdx":3528},{"frame":734,"entryIdx":3529},{"frame":735,"entryIdx":3530},{"frame":736,"entryIdx":3531},{"frame":737,"entryIdx":3532},{"frame":738,"entryIdx":3533},{"frame":739,"entryIdx":3534},{"frame":740,"entryIdx":3535},{"frame":741,"entryIdx":3536},{"frame":742,"entryIdx":3537},{"frame":743,"entryIdx":3538},{"frame":744,"entryIdx":3539},{"frame":745,"entryIdx":3540},{"frame":746,"entryIdx":3541},{"frame":747,"entryIdx":3542},{"frame":748,"entryIdx":3543},{"frame":749,"entryIdx":3544},{"frame":750,"entryIdx":3545},{"frame":751,"entryIdx":3546},{"frame":752,"entryIdx":3547},{"frame":753,"entryIdx":3548},{"frame":754,"entryIdx":3549},{"frame":755,"entryIdx":3550},{"frame":756,"entryIdx":3704},{"frame":757,"entryIdx":3705},{"frame":758,"entryIdx":3706},{"frame":759,"entryIdx":3707},{"frame":760,"entryIdx":3708},{"frame":761,"entryIdx":3709},{"frame":762,"entryIdx":3710},{"frame":763,"entryIdx":3711},{"frame":764,"entryIdx":4038},{"frame":765,"entryIdx":4039},{"frame":766,"entryIdx":4040},{"frame":767,"entryIdx":4041},{"frame":768,"entryIdx":4042},{"frame":769,"entryIdx":4043},{"frame":770,"entryIdx":4044},{"frame":771,"entryIdx":4045},{"frame":772,"entryIdx":4046},{"frame":773,"entryIdx":4047},{"frame":774,"entryIdx":4048},{"frame":775,"entryIdx":4049},{"frame":776,"entryIdx":4050},{"frame":777,"entryIdx":4051},{"frame":778,"entryIdx":4052},{"frame":779,"entryIdx":4053},{"frame":780,"entryIdx":4054},{"frame":781,"entryIdx":4055},{"frame":782,"entryIdx":4056},{"frame":783,"entryIdx":4057},{"frame":784,"entryIdx":4058},{"frame":785,"entryIdx":4059},{"frame":786,"entryIdx":4060},{"frame":787,"entryIdx":4061},{"frame":788,"entryIdx":4062},{"frame":789,"entryIdx":4063},{"frame":790,"entryIdx":4064},{"frame":791,"entryIdx":4065},{"frame":792,"entryIdx":4066},{"frame":793,"entryIdx":4067},{"frame":794,"entryIdx":4068},{"frame":795,"entryIdx":4360},{"frame":796,"entryIdx":4361},{"frame":797,"entryIdx":4362},{"frame":798,"entryIdx":4363},{"frame":799,"entryIdx":4364},{"frame":800,"entryIdx":4365},{"frame":801,"entryIdx":4366},{"frame":802,"entryIdx":4367},{"frame":803,"entryIdx":4368},{"frame":804,"entryIdx":4369},{"frame":805,"entryIdx":4370},{"frame":806,"entryIdx":4371},{"frame":807,"entryIdx":4372},{"frame":808,"entryIdx":4373},{"frame":809,"entryIdx":4374},{"frame":810,"entryIdx":4375},{"frame":811,"entryIdx":4376},{"frame":812,"entryIdx":4377},{"frame":813,"entryIdx":4378},{"frame":814,"entryIdx":4379},{"frame":815,"entryIdx":4380},{"frame":816,"entryIdx":4381},{"frame":817,"entryIdx":4382},{"frame":818,"entryIdx":4383},{"frame":819,"entryIdx":4384},{"frame":820,"entryIdx":4385},{"frame":821,"entryIdx":4386},{"frame":822,"entryIdx":4387},{"frame":823,"entryIdx":4388},{"frame":824,"entryIdx":4389},{"frame":825,"entryIdx":4390},{"frame":826,"entryIdx":4391},{"frame":827,"entryIdx":4392},{"frame":828,"entryIdx":4393},{"frame":829,"entryIdx":4394},{"frame":830,"entryIdx":4395},{"frame":831,"entryIdx":4396},{"frame":832,"entryIdx":4397},{"frame":833,"entryIdx":4398},{"frame":834,"entryIdx":4399},{"frame":835,"entryIdx":4400},{"frame":836,"entryIdx":4401},{"frame":837,"entryIdx":4402},{"frame":838,"entryIdx":4403},{"frame":839,"entryIdx":4404},{"frame":840,"entryIdx":4405},{"frame":841,"entryIdx":4406},{"frame":842,"entryIdx":4407},{"frame":843,"entryIdx":4408},{"frame":844,"entryIdx":4409},{"frame":845,"entryIdx":4410},{"frame":846,"entryIdx":4411},{"frame":847,"entryIdx":4412},{"frame":848,"entryIdx":4413},{"frame":849,"entryIdx":4414},{"frame":850,"entryIdx":4415},{"frame":851,"entryIdx":4416},{"frame":852,"entryIdx":4417},{"frame":853,"entryIdx":4418},{"frame":854,"entryIdx":4419},{"frame":855,"entryIdx":4420},{"frame":856,"entryIdx":4421},{"frame":857,"entryIdx":4422},{"frame":858,"entryIdx":4423},{"frame":859,"entryIdx":4424},{"frame":880,"entryIdx":4555},{"frame":881,"entryIdx":4556},{"frame":882,"entryIdx":4557},{"frame":883,"entryIdx":4558},{"frame":884,"entryIdx":4559},{"frame":885,"entryIdx":4560},{"frame":860,"entryIdx":4561},{"frame":861,"entryIdx":4562},{"frame":862,"entryIdx":4563},{"frame":863,"entryIdx":4564},{"frame":864,"entryIdx":4565},{"frame":865,"entryIdx":4566},{"frame":866,"entryIdx":4567},{"frame":867,"entryIdx":4568},{"frame":868,"entryIdx":4569},{"frame":869,"entryIdx":4570},{"frame":870,"entryIdx":4571},{"frame":871,"entryIdx":4572},{"frame":872,"entryIdx":4573},{"frame":873,"entryIdx":4574},{"frame":874,"entryIdx":4575},{"frame":875,"entryIdx":4576},{"frame":876,"entryIdx":4577},{"frame":877,"entryIdx":4578},{"frame":878,"entryIdx":4579},{"frame":879,"entryIdx":4580},{"frame":886,"entryIdx":4639},{"frame":887,"entryIdx":4640},{"frame":888,"entryIdx":4641},{"frame":889,"entryIdx":4642},{"frame":890,"entryIdx":4643},{"frame":891,"entryIdx":4644},{"frame":892,"entryIdx":4645},{"frame":893,"entryIdx":4646},{"frame":894,"entryIdx":4647},{"frame":895,"entryIdx":4648},{"frame":896,"entryIdx":4649},{"frame":897,"entryIdx":4650},{"frame":898,"entryIdx":4651},{"frame":899,"entryIdx":4652},{"frame":900,"entryIdx":4653},{"frame":901,"entryIdx":4654},{"frame":902,"entryIdx":4655},{"frame":903,"entryIdx":4656},{"frame":904,"entryIdx":4657},{"frame":905,"entryIdx":4658},{"frame":906,"entryIdx":4659},{"frame":907,"entryIdx":4660},{"frame":908,"entryIdx":4661},{"frame":909,"entryIdx":4662},{"frame":910,"entryIdx":4663},{"frame":911,"entryIdx":4664},{"frame":912,"entryIdx":4665},{"frame":913,"entryIdx":4666},{"frame":914,"entryIdx":4667},{"frame":915,"entryIdx":4668},{"frame":916,"entryIdx":4669},{"frame":917,"entryIdx":4670},{"frame":918,"entryIdx":4671},{"frame":919,"entryIdx":4672},{"frame":920,"entryIdx":4673},{"frame":921,"entryIdx":4674},{"frame":922,"entryIdx":4675},{"frame":923,"entryIdx":4676},{"frame":924,"entryIdx":4677},{"frame":925,"entryIdx":4678},{"frame":926,"entryIdx":4679},{"frame":927,"entryIdx":4680},{"frame":928,"entryIdx":4681},{"frame":929,"entryIdx":4682},{"frame":930,"entryIdx":4683},{"frame":931,"entryIdx":4684},{"frame":932,"entryIdx":4685},{"frame":933,"entryIdx":4686},{"frame":934,"entryIdx":4687},{"frame":935,"entryIdx":4688},{"frame":936,"entryIdx":4689},{"frame":937,"entryIdx":4690},{"frame":938,"entryIdx":4691},{"frame":939,"entryIdx":4692},{"frame":940,"entryIdx":4693},{"frame":941,"entryIdx":4694},{"frame":942,"entryIdx":4695},{"frame":943,"entryIdx":4696},{"frame":944,"entryIdx":4697},{"frame":945,"entryIdx":4698},{"frame":946,"entryIdx":4699},{"frame":947,"entryIdx":4700},{"frame":948,"entryIdx":4701},{"frame":949,"entryIdx":4702},{"frame":950,"entryIdx":4703},{"frame":951,"entryIdx":4704},{"frame":952,"entryIdx":4705},{"frame":953,"entryIdx":4706},{"frame":954,"entryIdx":4707},{"frame":955,"entryIdx":4708},{"frame":956,"entryIdx":4709},{"frame":957,"entryIdx":4710},{"frame":958,"entryIdx":4711},{"frame":959,"entryIdx":4712},{"frame":960,"entryIdx":4713},{"frame":961,"entryIdx":4714},{"frame":962,"entryIdx":4715},{"frame":963,"entryIdx":4716},{"frame":964,"entryIdx":4717},{"frame":965,"entryIdx":4718},{"frame":966,"entryIdx":4719},{"frame":967,"entryIdx":4720},{"frame":968,"entryIdx":4721},{"frame":969,"entryIdx":4722},{"frame":970,"entryIdx":4723},{"frame":971,"entryIdx":4724},{"frame":972,"entryIdx":4725},{"frame":973,"entryIdx":4726},{"frame":974,"entryIdx":4727},{"frame":975,"entryIdx":4728},{"frame":976,"entryIdx":4729},{"frame":977,"entryIdx":4730},{"frame":978,"entryIdx":4731},{"frame":979,"entryIdx":4732},{"frame":980,"entryIdx":4733},{"frame":981,"entryIdx":4734},{"frame":982,"entryIdx":4735},{"frame":983,"entryIdx":4736},{"frame":984,"entryIdx":4737},{"frame":985,"entryIdx":4738},{"frame":986,"entryIdx":4739},{"frame":987,"entryIdx":4740},{"frame":988,"entryIdx":4741},{"frame":989,"entryIdx":4742},{"frame":990,"entryIdx":4743},{"frame":991,"entryIdx":4744},{"frame":992,"entryIdx":4745},{"frame":993,"entryIdx":4746},{"frame":994,"entryIdx":4747},{"frame":995,"entryIdx":4748},{"frame":996,"entryIdx":4749},{"frame":997,"entryIdx":4750},{"frame":998,"entryIdx":4751},{"frame":999,"entryIdx":4752},{"frame":1000,"entryIdx":4753},{"frame":1001,"entryIdx":4754},{"frame":1002,"entryIdx":4755},{"frame":1003,"entryIdx":4756},{"frame":1004,"entryIdx":4757},{"frame":1005,"entryIdx":4758},{"frame":1006,"entryIdx":4759},{"frame":1007,"entryIdx":4760},{"frame":1008,"entryIdx":4761},{"frame":1009,"entryIdx":4762},{"frame":1010,"entryIdx":4763},{"frame":1011,"entryIdx":4764},{"frame":1012,"entryIdx":4765},{"frame":1013,"entryIdx":4766},{"frame":1014,"entryIdx":4767},{"frame":1015,"entryIdx":4768},{"frame":1016,"entryIdx":4769},{"frame":1017,"entryIdx":4770},{"frame":1018,"entryIdx":4771},{"frame":1019,"entryIdx":4772},{"frame":1020,"entryIdx":4773},{"frame":1021,"entryIdx":4774},{"frame":1022,"entryIdx":4775},{"frame":1023,"entryIdx":4776},{"frame":1024,"entryIdx":4777},{"frame":1025,"entryIdx":4778},{"frame":1026,"entryIdx":4779},{"frame":1027,"entryIdx":4780},{"frame":1028,"entryIdx":4781},{"frame":1029,"entryIdx":4782},{"frame":1030,"entryIdx":4783},{"frame":1031,"entryIdx":4784},{"frame":1032,"entryIdx":4785},{"frame":1033,"entryIdx":4786},{"frame":1034,"entryIdx":4787},{"frame":1035,"entryIdx":4788},{"frame":1036,"entryIdx":4789},{"frame":1037,"entryIdx":4790},{"frame":1038,"entryIdx":4791},{"frame":1039,"entryIdx":4792},{"frame":1040,"entryIdx":4793},{"frame":1041,"entryIdx":4794},{"frame":1042,"entryIdx":4795},{"frame":1043,"entryIdx":4796},{"frame":1044,"entryIdx":4797},{"frame":1045,"entryIdx":4798},{"frame":1046,"entryIdx":4799},{"frame":1047,"entryIdx":4800},{"frame":1048,"entryIdx":4801},{"frame":1049,"entryIdx":4802},{"frame":1050,"entryIdx":4803},{"frame":1051,"entryIdx":4804},{"frame":1052,"entryIdx":4805},{"frame":1053,"entryIdx":4806},{"frame":1054,"entryIdx":4807},{"frame":1055,"entryIdx":4808},{"frame":1056,"entryIdx":4809},{"frame":1057,"entryIdx":4810},{"frame":1058,"entryIdx":4811},{"frame":1059,"entryIdx":4812},{"frame":1060,"entryIdx":4813},{"frame":1061,"entryIdx":4814},{"frame":1062,"entryIdx":4815},{"frame":1063,"entryIdx":4816},{"frame":1064,"entryIdx":4966},{"frame":1065,"entryIdx":4967},{"frame":1066,"entryIdx":4968},{"frame":1067,"entryIdx":4969},{"frame":1068,"entryIdx":4970},{"frame":1069,"entryIdx":4971},{"frame":1070,"entryIdx":4972},{"frame":1071,"entryIdx":4973},{"frame":1072,"entryIdx":4974},{"frame":1073,"entryIdx":4975},{"frame":1074,"entryIdx":4976},{"frame":1075,"entryIdx":4977},{"frame":1076,"entryIdx":4978},{"frame":1077,"entryIdx":4979},{"frame":1078,"entryIdx":4980},{"frame":1079,"entryIdx":4981},{"frame":1080,"entryIdx":4982},{"frame":1081,"entryIdx":4983},{"frame":1082,"entryIdx":4984},{"frame":1083,"entryIdx":4985},{"frame":1084,"entryIdx":4986},{"frame":1085,"entryIdx":4987},{"frame":1086,"entryIdx":4988},{"frame":1087,"entryIdx":4989},{"frame":1088,"entryIdx":4990},{"frame":1089,"entryIdx":4991},{"frame":1090,"entryIdx":4992},{"frame":1091,"entryIdx":4993},{"frame":1092,"entryIdx":4994},{"frame":1093,"entryIdx":4995},{"frame":1094,"entryIdx":4996},{"frame":1095,"entryIdx":4997},{"frame":1096,"entryIdx":4998},{"frame":1097,"entryIdx":4999},{"frame":1098,"entryIdx":5000},{"frame":1099,"entryIdx":5001},{"frame":1100,"entryIdx":5002},{"frame":1101,"entryIdx":5003},{"frame":1102,"entryIdx":5004},{"frame":1103,"entryIdx":5005},{"frame":1104,"entryIdx":5006},{"frame":1105,"entryIdx":5007},{"frame":1106,"entryIdx":5008},{"frame":1107,"entryIdx":5009},{"frame":1108,"entryIdx":5010},{"frame":1109,"entryIdx":5011},{"frame":1110,"entryIdx":5012},{"frame":1111,"entryIdx":5013},{"frame":1112,"entryIdx":5014},{"frame":1113,"entryIdx":5015},{"frame":1114,"entryIdx":5016},{"frame":1115,"entryIdx":5017},{"frame":1116,"entryIdx":5018},{"frame":1117,"entryIdx":5019},{"frame":1118,"entryIdx":5020},{"frame":1119,"entryIdx":5021},{"frame":1120,"entryIdx":5022},{"frame":1121,"entryIdx":5023},{"frame":1122,"entryIdx":5024},{"frame":1123,"entryIdx":5025},{"frame":1124,"entryIdx":5026},{"frame":1125,"entryIdx":5027},{"frame":1126,"entryIdx":5028},{"frame":1127,"entryIdx":5029},{"frame":1128,"entryIdx":5030},{"frame":1129,"entryIdx":5031},{"frame":1130,"entryIdx":5032},{"frame":1131,"entryIdx":5033},{"frame":1132,"entryIdx":5034},{"frame":1133,"entryIdx":5035},{"frame":1134,"entryIdx":5036},{"frame":1135,"entryIdx":5037},{"frame":1136,"entryIdx":5038},{"frame":1137,"entryIdx":5039},{"frame":1138,"entryIdx":5040},{"frame":1139,"entryIdx":5041},{"frame":1140,"entryIdx":5042},{"frame":1141,"entryIdx":5043},{"frame":1142,"entryIdx":5044},{"frame":1143,"entryIdx":5045},{"frame":1144,"entryIdx":5046},{"frame":1145,"entryIdx":5047},{"frame":1146,"entryIdx":5048},{"frame":1147,"entryIdx":5049},{"frame":1148,"entryIdx":5050},{"frame":1149,"entryIdx":5051},{"frame":1150,"entryIdx":5052},{"frame":1151,"entryIdx":5053},{"frame":1152,"entryIdx":5054},{"frame":1153,"entryIdx":5055},{"frame":1154,"entryIdx":5056},{"frame":1155,"entryIdx":5057},{"frame":1156,"entryIdx":5058},{"frame":1157,"entryIdx":5252},{"frame":1158,"entryIdx":5253},{"frame":1159,"entryIdx":5254},{"frame":1160,"entryIdx":5255},{"frame":1161,"entryIdx":5256},{"frame":1162,"entryIdx":5257},{"frame":1163,"entryIdx":5258},{"frame":1164,"entryIdx":5259},{"frame":1165,"entryIdx":5260},{"frame":1166,"entryIdx":5261},{"frame":1167,"entryIdx":5262},{"frame":1168,"entryIdx":5263},{"frame":1169,"entryIdx":5264},{"frame":1170,"entryIdx":5265},{"frame":1171,"entryIdx":5266},{"frame":1172,"entryIdx":5267},{"frame":1173,"entryIdx":5268},{"frame":1174,"entryIdx":5269},{"frame":1175,"entryIdx":5270},{"frame":1176,"entryIdx":5271},{"frame":1177,"entryIdx":5272},{"frame":1178,"entryIdx":5273},{"frame":1179,"entryIdx":5274},{"frame":1180,"entryIdx":5275},{"frame":1181,"entryIdx":5276},{"frame":1182,"entryIdx":5277},{"frame":1183,"entryIdx":5278},{"frame":1184,"entryIdx":5279},{"frame":1185,"entryIdx":5280},{"frame":1186,"entryIdx":5281},{"frame":1187,"entryIdx":5282},{"frame":1188,"entryIdx":5283},{"frame":1189,"entryIdx":5284},{"frame":1190,"entryIdx":5285},{"frame":1191,"entryIdx":5286},{"frame":1192,"entryIdx":5287},{"frame":1193,"entryIdx":5288},{"frame":1194,"entryIdx":5289},{"frame":1195,"entryIdx":5290},{"frame":1196,"entryIdx":5392},{"frame":1197,"entryIdx":5393},{"frame":1198,"entryIdx":5394},{"frame":1199,"entryIdx":5395},{"frame":1200,"entryIdx":5396},{"frame":1201,"entryIdx":5397},{"frame":1202,"entryIdx":5398},{"frame":1203,"entryIdx":5399},{"frame":1204,"entryIdx":5400},{"frame":1205,"entryIdx":5401},{"frame":1206,"entryIdx":5402},{"frame":1207,"entryIdx":5403},{"frame":1208,"entryIdx":5404},{"frame":1209,"entryIdx":5405},{"frame":1210,"entryIdx":5406},{"frame":1211,"entryIdx":5407},{"frame":1212,"entryIdx":5408},{"frame":1213,"entryIdx":5409},{"frame":1214,"entryIdx":5410},{"frame":1215,"entryIdx":5411},{"frame":1216,"entryIdx":5412},{"frame":1217,"entryIdx":5413},{"frame":1218,"entryIdx":5414},{"frame":1219,"entryIdx":5415},{"frame":1220,"entryIdx":5416},{"frame":1221,"entryIdx":5417},{"frame":1222,"entryIdx":5418},{"frame":1223,"entryIdx":5419},{"frame":1224,"entryIdx":5420},{"frame":1225,"entryIdx":5421},{"frame":1226,"entryIdx":5422},{"frame":1227,"entryIdx":5423},{"frame":1228,"entryIdx":5424},{"frame":1229,"entryIdx":5425},{"frame":1230,"entryIdx":5426},{"frame":1231,"entryIdx":5427},{"frame":1232,"entryIdx":5428},{"frame":1233,"entryIdx":5429},{"frame":1234,"entryIdx":5430},{"frame":1235,"entryIdx":5431},{"frame":1236,"entryIdx":5432},{"frame":1237,"entryIdx":5433},{"frame":1238,"entryIdx":5518},{"frame":1239,"entryIdx":5519},{"frame":1240,"entryIdx":5520},{"frame":1241,"entryIdx":5521},{"frame":1242,"entryIdx":5522}]